naruhodo/__init__.py
naruhodo/backends/__init__.py
naruhodo/backends/cabocha.py
naruhodo/core/DependencyCoreJa.py
naruhodo/core/KnowledgeCoreJa.py
naruhodo/core/__init__.py
naruhodo/core/parser.py
naruhodo/utils/__init__.py
naruhodo/utils/communication.py
naruhodo/utils/dicts.py
naruhodo/utils/misc.py
naruhodo/utils/polarity.py
naruhodo/utils/scraper.py
naruhodo-0.2.9.dist-info/DESCRIPTION.rst
naruhodo-0.2.9.dist-info/METADATA
naruhodo-0.2.9.dist-info/RECORD
naruhodo-0.2.9.dist-info/WHEEL
naruhodo-0.2.9.dist-info/metadata.json
naruhodo-0.2.9.dist-info/top_level.txt
test/backends/__init__.py
test/backends/test_cabocha.py
test/utils/__init__.py
test/utils/test_scraper.py
