Metadata-Version: 2.0
Name: naruhodo
Version: 0.2.9
Summary: A python library for automatic semantic graph generation from human-readable text.
Home-page: https://github.com/superkerokero/naruhodo
Author: superkerokero
Author-email: superkerokero@outlook.com
License: MIT
Download-URL: https://github.com/superkerokero/naruhodo/archive/master.zip
Keywords: nlp,knowledge graph,knowledge representation,japanese
Platform: UNKNOWN
Requires-Python: >=3.4
Requires-Dist: networkx
Requires-Dist: beautifulsoup4
Requires-Dist: nxpd
Requires-Dist: lxml
